{
    "FileInfo": {
        "BA01": {
            "MasterFile": "2024-08-07T08:17:31.146122",
            "DealerInfo": "2024-08-07T22:39:28.247616",
            "KAList": null
        },
        "BA02": {
            "MasterFile": "2024-08-07T08:17:31.193461",
            "DealerInfo": "2024-08-07T08:17:31.227745",
            "KAList": null
        },
        "BA03": {
            "MasterFile": "2024-08-07T08:17:31.237296",
            "DealerInfo": "2024-08-07T22:22:09.188019",
            "KAList": null
        },
        "BA04": {
            "MasterFile": "2024-08-07T08:17:31.274915",
            "DealerInfo": "2024-08-07T08:17:31.304262",
            "KAList": null
        }
    },
    "System": {
        "Config1": {
            "FileName": "",
            "FileWriteTime": ""
        }
    }
}